gatenlphiltlab/__init__.py
gatenlphiltlab/regex_patterns.py
gatenlphiltlab/diff/__init__.py
gatenlphiltlab-4.0.5.dist-info/LICENSE.md
gatenlphiltlab-4.0.5.dist-info/METADATA
gatenlphiltlab-4.0.5.dist-info/WHEEL
gatenlphiltlab-4.0.5.dist-info/top_level.txt
gatenlphiltlab-4.0.5.dist-info/RECORD
